[
  {
    "paymentIntentId": "pi_3OJ6oNSENcdZfgNi1L3hYOh5",
    "orderId": "ORDER-ae55-117",
    "paymentStatus": "success",
    "transactionId": "pi_3OJ6oNSENcdZfgNi1L3hYOh5",
    "MOP": "card"
  },
  {
    "paymentIntentId": "pi_3OJ6ubSENcdZfgNi1Hk3MzBR",
    "orderId": "ORDER-ae55-119",
    "paymentStatus": "success",
    "transactionId": "pi_3OJ6ubSENcdZfgNi1Hk3MzBR",
    "MOP": "card"
  },
  {
    "paymentIntentId": "pi_3OJ6wkSENcdZfgNi059t88xD",
    "orderId": "ORDER-ae55-1110",
    "paymentStatus": "success",
    "transactionId": "pi_3OJ6wkSENcdZfgNi059t88xD",
    "MOP": "card"
  },
  {
    "paymentIntentId": "pi_3OJ6ypSENcdZfgNi08ollEeY",
    "orderId": "ORDER-ae55-1111",
    "paymentStatus": "success",
    "transactionId": "pi_3OJ6ypSENcdZfgNi08ollEeY",
    "MOP": "card"
  },
  {
    "paymentIntentId": "pi_3OJ73rSENcdZfgNi12ExQamZ",
    "orderId": "ORDER-ae55-1113",
    "paymentStatus": "success",
    "transactionId": "pi_3OJ73rSENcdZfgNi12ExQamZ",
    "MOP": "card"
  },
  {
    "paymentIntentId": "pi_3OJ7HZSENcdZfgNi15yWPKh6",
    "orderId": "ORDER-ae55-1117",
    "paymentStatus": "success",
    "transactionId": "pi_3OJ7HZSENcdZfgNi15yWPKh6",
    "MOP": "card"
  }
]